Workbook

Sheet Main
A1: Land (NL) | B1: Country | C1: CountryCode | D1: Countrycode 3 | E1: Currency | F1: Currency Code 3 dig | G1: Language | H1: Lang. in CM | I1: Phone nr | J1: Web | K1: Continent | L1: Region 1 | M1: Region 2
A2: Algerije | B2: Algeria | C2: DZ | D2: DZA | E2: Algerian Dinar | F2: DZD | G2: AR | H2: EN | I2: +213 | J2: =_xlfn.XLOOKUP(C2,'ISO overview'!A:A,'ISO overview'!J:J) -> .dz | K2: Africa | L2: Northern Africa | M2: =L2 -> Northern Africa
A3: Egypte | B3: Egypt | C3: EG | D3: EGY | E3: Egyptian Pound | F3: EGP | G3: AR | H3: EN | I3: +20 | J3: =_xlfn.XLOOKUP(C3,'ISO overview'!A:A,'ISO overview'!J:J) -> .eg | K3: Africa | L3: Northern Africa | M3: =L3 -> Northern Africa
A4: Libië | B4: Libyan Arab Jamahiriya | C4: LY | D4: LBY | E4: Libyan Dinar | F4: LYD | G4: AR | H4: EN | I4: +218 | J4: =_xlfn.XLOOKUP(C4,'ISO overview'!A:A,'ISO overview'!J:J) -> .ly | K4: Africa | L4: Northern Africa | M4: =L4 -> Northern Africa
A5: Marokko | B5: Morocco | C5: MA | D5: MAR | E5: Dirham | F5: MAD | G5: AR | H5: EN | I5: +212 | J5: =_xlfn.XLOOKUP(C5,'ISO overview'!A:A,'ISO overview'!J:J) -> .ma | K5: Africa | L5: Northern Africa | M5: =L5 -> Northern Africa
A6: Soedan | B6: Sudan | C6: SD | D6: SDN | E6: Dinar | F6: SDG | G6: AR | H6: EN | I6: +249 | J6: =_xlfn.XLOOKUP(C6,'ISO overview'!A:A,'ISO overview'!J:J) -> .sd | K6: Africa | L6: Northern Africa | M6: =L6 -> Northern Africa
A7: Tunesië | B7: Tunisia | C7: TN | D7: TUN | E7: Tunisian Dinar | F7: TND | G7: AR | H7: EN | I7: +216 | J7: =_xlfn.XLOOKUP(C7,'ISO overview'!A:A,'ISO overview'!J:J) -> .tn | K7: Africa | L7: Northern Africa | M7: =L7 -> Northern Africa
B8: Western Sahara | C8: EH | D8: ESH | E8: Dirham | F8: MAD | G8: AR | H8: EN | I8: +212 | J8: =_xlfn.XLOOKUP(C8,'ISO overview'!A:A,'ISO overview'!J:J) -> .eh | K8: Africa | L8: Northern Africa | M8: =L8 -> Northern Africa
B9: British Indian Ocean Territory | C9: IO | D9: IOT | E9: USD | F9: USD | G9: EN | H9: EN | I9: +246 | J9: =_xlfn.XLOOKUP(C9,'ISO overview'!A:A,'ISO overview'!J:J) -> .io | K9: Africa | L9: Sub-Saharan Africa | M9: Eastern Africa
A10: Burundi | B10: Burundi | C10: BI | D10: BDI | E10: Burundi Franc | F10: BIF | G10: FR | H10: FR | I10: +257 | J10: =_xlfn.XLOOKUP(C10,'ISO overview'!A:A,'ISO overview'!J:J) -> .bi | K10: Africa | L10: Sub-Saharan Africa | M10: Eastern Africa
A11: de Comore | B11: Comoros | C11: KM | D11: COM | E11: Comoran Franc | F11: KMF | G11: AR | H11: EN | I11: +269 | J11: =_xlfn.XLOOKUP(C11,'ISO overview'!A:A,'ISO overview'!J:J) -> .km | K11: Africa | L11: Sub-Saharan Africa | M11: Eastern Africa
A12: Djibouti | B12: Djibouti | C12: DJ | D12: DJI | E12: Djiboutian Franc | F12: DJF | G12: FR | H12: FR | I12: +253 | J12: =_xlfn.XLOOKUP(C12,'ISO overview'!A:A,'ISO overview'!J:J) -> .dj | K12: Africa | L12: Sub-Saharan Africa | M12: Eastern Africa
A13: Eritrea | B13: Eritrea | C13: ER | D13: ERI | E13: Ethiopian Birr | F13: ETB | G13: AA | H13: EN | I13: +291 | J13: =_xlfn.XLOOKUP(C13,'ISO overview'!A:A,'ISO overview'!J:J) -> .er | K13: Africa | L13: Sub-Saharan Africa | M13: Eastern Africa
A14: Ethiopië | B14: Ethiopia | C14: ET | D14: ETH | E14: Ethiopian Birr | F14: ETB | G14: AM | H14: EN | I14: +251 | J14: =_xlfn.XLOOKUP(C14,'ISO overview'!A:A,'ISO overview'!J:J) -> .et | K14: Africa | L14: Sub-Saharan Africa | M14: Eastern Africa
B15: French Southern Territories | C15: TF | D15: ATF | E15: Euros | F15: EUR | G15: FR | H15: FR | I15: + | J15: =_xlfn.XLOOKUP(C15,'ISO overview'!A:A,'ISO overview'!J:J) -> .tf | K15: Africa | L15: Sub-Saharan Africa | M15: Eastern Africa
A16: Kenia | B16: Kenya | C16: KE | D16: KEN | E16: Kenyan Shilling | F16: KES | G16: EN | H16: EN | I16: +254 | J16: =_xlfn.XLOOKUP(C16,'ISO overview'!A:A,'ISO overview'!J:J) -> .ke | K16: Africa | L16: Sub-Saharan Africa | M16: Eastern Africa
A17: Madagaskar | B17: Madagascar | C17: MG | D17: MDG | E17: Malagasy Franc | F17: MGA | G17: FR | H17: FR | I17: +261 | J17: =_xlfn.XLOOKUP(C17,'ISO overview'!A:A,'ISO overview'!J:J) -> .mg | K17: Africa | L17: Sub-Saharan Africa | M17: Eastern Africa
A18: Malawi | B18: Malawi | C18: MW | D18: MWI | E18: Malawian Kwacha | F18: MWK | G18: NY | H18: EN | I18: +265 | J18: =_xlfn.XLOOKUP(C18,'ISO overview'!A:A,'ISO overview'!J:J) -> .mw | K18: Africa | L18: Sub-Saharan Africa | M18: Eastern Africa
A19: Mauritius | B19: Mauritius | C19: MU | D19: MUS | E19: Mauritian Rupee | F19: MUR | G19: EN | H19: EN | I19: +230 | J19: =_xlfn.XLOOKUP(C19,'ISO overview'!A:A,'ISO overview'!J:J) -> .mu | K19: Africa | L19: Sub-Saharan Africa | M19: Eastern Africa
B20: Mayotte | C20: YT | D20: MYT | E20: Euros | F20: EUR | G20: FR | H20: FR | I20: +262 | J20: =_xlfn.XLOOKUP(C20,'ISO overview'!A:A,'ISO overview'!J:J) -> .yt | K20: Africa | L20: Sub-Saharan Africa | M20: Eastern Africa
A21: Mozambique | B21: Mozambique | C21: MZ | D21: MOZ | E21: Metical | F21: MZN | G21: PT | H21: PT | I21: +258 | J21: =_xlfn.XLOOKUP(C21,'ISO overview'!A:A,'ISO overview'!J:J) -> .mz | K21: Africa | L21: Sub-Saharan Africa | M21: Eastern Africa
B22: Reunion | C22: RE | D22: REU | E22: Euros | F22: EUR | G22: FR | H22: FR | I22: +262 | J22: =_xlfn.XLOOKUP(C22,'ISO overview'!A:A,'ISO overview'!J:J) -> .re | K22: Africa | L22: Sub-Saharan Africa | M22: Eastern Africa
A23: Rwanda | B23: Rwanda | C23: RW | D23: RWA | E23: Rwanda Franc | F23: RWF | G23: RW | H23: EN | I23: +250 | J23: =_xlfn.XLOOKUP(C23,'ISO overview'!A:A,'ISO overview'!J:J) -> .rw | K23: Africa | L23: Sub-Saharan Africa | M23: Eastern Africa
A24: de Seychelle | B24: Seychelles | C24: SC | D24: SYC | E24: Rupee | F24: SCR | G24: EN | H24: EN | I24: +248 | J24: =_xlfn.XLOOKUP(C24,'ISO overview'!A:A,'ISO overview'!J:J) -> .sc | K24: Africa | L24: Sub-Saharan Africa | M24: Eastern Africa
A25: Somalië | B25: Somalia | C25: SO | D25: SOM | E25: Shilling | F25: SOS | G25: SO | H25: EN | I25: +252 | J25: =_xlfn.XLOOKUP(C25,'ISO overview'!A:A,'ISO overview'!J:J) -> .so | K25: Africa | L25: Sub-Saharan Africa | M25: Eastern Africa
A26: Tanzania | B26: Tanzania | C26: TZ | D26: TZA | E26: Shilling | F26: TZS | G26: SW | H26: EN | I26: +255 | J26: =_xlfn.XLOOKUP(C26,'ISO overview'!A:A,'ISO overview'!J:J) -> .tz | K26: Africa | L26: Sub-Saharan Africa | M26: Eastern Africa
A27: Oeganda | B27: Uganda | C27: UG | D27: UGA | E27: Shilling | F27: UGX | G27: EN | H27: EN | I27: +256 | J27: =_xlfn.XLOOKUP(C27,'ISO overview'!A:A,'ISO overview'!J:J) -> .ug | K27: Africa | L27: Sub-Saharan Africa | M27: Eastern Africa
A28: Zambia Z | B28: Zambia | C28: ZM | D28: ZMB | E28: Kwacha | F28: ZMK | G28: EN | H28: EN | I28: +260 | J28: =_xlfn.XLOOKUP(C28,'ISO overview'!A:A,'ISO overview'!J:J) -> .zm | K28: Africa | L28: Sub-Saharan Africa | M28: Eastern Africa
A29: Zimbabwe | B29: Zimbabwe | C29: ZW | D29: ZWE | E29: Zimbabwe Dollar | F29: ZWD | G29: EN | H29: EN | I29: +263 | J29: =_xlfn.XLOOKUP(C29,'ISO overview'!A:A,'ISO overview'!J:J) -> .zw | K29: Africa | L29: Sub-Saharan Africa | M29: Eastern Africa
A30: Angola | B30: Angola | C30: AO | D30: AGO | E30: Angolan kwanza | F30: AOA | G30: PT | H30: PT | I30: +244 | J30: =_xlfn.XLOOKUP(C30,'ISO overview'!A:A,'ISO overview'!J:J) -> .ao | K30: Africa | L30: Sub-Saharan Africa | M30: Middle Africa
A31: Kameroen | B31: Cameroon | C31: CM | D31: CMR | E31: CFA Franc BEAC | F31: XAF | G31: EN | H31: EN | I31: +237 | J31: =_xlfn.XLOOKUP(C31,'ISO overview'!A:A,'ISO overview'!J:J) -> .cm | K31: Africa | L31: Sub-Saharan Africa | M31: Middle Africa
A32: de Centraal-Afrikaanse Republie | B32: Central African Republic | C32: CF | D32: CAF | E32: CFA Franc BEAC | F32: XAF | G32: FR | H32: FR | I32: +236 | J32: =_xlfn.XLOOKUP(C32,'ISO overview'!A:A,'ISO overview'!J:J) -> .cf | K32: Africa | L32: Sub-Saharan Africa | M32: Middle Africa
A33: Tsjaad | B33: Chad | C33: TD | D33: TCD | E33: CFA Franc BEAC | F33: XAF | G33: FR | H33: FR | I33: +235 | J33: =_xlfn.XLOOKUP(C33,'ISO overview'!A:A,'ISO overview'!J:J) -> .td | K33: Africa | L33: Sub-Saharan Africa | M33: Middle Africa
A34: Congo-Kinshasa | B34: Congo (Kinshasa) | C34: CD | D34: COD | E34: Congolese Frank | F34: CDF | G34: FR | H34: FR | I34: +243 | J34: =_xlfn.XLOOKUP(C34,'ISO overview'!A:A,'ISO overview'!J:J) -> .cd | K34: Africa | L34: Sub-Saharan Africa | M34: Middle Africa
... A57: Nigeria | B57: Nigeria | C57: NG | D57: NGA | E57: Naira | F57: NGN | G57: EN | H57: EN | I57: +234 | J57: =_xlfn.XLOOKUP(C57,'ISO overview'!A:A,'ISO overview'!J:J) -> .ng | K57: Africa | L57: Sub-Saharan Africa | M57: Western Africa
B58: Saint Helena | C58: SH | D58: SHN | E58: Saint Helena pound | F58: GBP | G58: EN | H58: EN | I58: +290 | J58: =_xlfn.XLOOKUP(C58,'ISO overview'!A:A,'ISO overview'!J:J) -> .sh | K58: Africa | L58: Sub-Saharan Africa | M58: Western Africa
A59: Senegal | B59: Senegal | C59: SN | D59: SEN | E59: CFA Franc BCEAO | F59: XOF | G59: FR | H59: FR | I59: +221 | J59: =_xlfn.XLOOKUP(C59,'ISO overview'!A:A,'ISO overview'!J:J) -> .sn | K59: Africa | L59: Sub-Saharan Africa | M59: Western Africa
A60: Sierra Leone | B60: Sierra Leone | C60: SL | D60: SLE | E60: Leone | F60: SLL | G60: EN | H60: EN | I60: +232 | J60: =_xlfn.XLOOKUP(C60,'ISO overview'!A:A,'ISO overview'!J:J) -> .sl | K60: Africa | L60: Sub-Saharan Africa | M60: Western Africa
A61: Togo | B61: Togo | C61: TG | D61: TGO | E61: CFA Franc BCEAO | F61: XOF | G61: FR | H61: FR | I61: +228 | J61: =_xlfn.XLOOKUP(C61,'ISO overview'!A:A,'ISO overview'!J:J) -> .tg | K61: Africa | L61: Sub-Saharan Africa | M61: Western Africa
B62: Antarctica | C62: AQ | D62: ATA | E62: Antarctican dollar | F62: AQD | G62: EN | H62: EN | I62: + | J62: =_xlfn.XLOOKUP(C62,'ISO overview'!A:A,'ISO overview'!J:J) -> .aq | K62: Antarctica | L62: Antarctica | M62: =L62 -> Antarctica
B63: East Timor | C63: TP | D63: #N/A | E63: Indonesian Rupiah | F63: IDR | G63: TO | H63: EN | I63: +676 | J63: =_xlfn.XLOOKUP(C63,'ISO overview'!A:A,'ISO overview'!J:J) -> #N/A | K63: Asia | L63: =K63 -> Asia | M63: =L63 -> Asia
A64: Taiwan | B64: Taiwan | C64: TW | D64: TWN | E64: Dollar | F64: TWD | G64: ZH | H64: EN | I64: +886 | J64: =_xlfn.XLOOKUP(C64,'ISO overview'!A:A,'ISO overview'!J:J) -> .tw | K64: Asia | L64: =K64 -> Asia | M64: =L64 -> Asia
A65: Kazachstan | B65: Kazakhstan | C65: KZ | D65: KAZ | E65: Tenge | F65: KZT | G65: KK | H65: EN | I65: +7 | J65: =_xlfn.XLOOKUP(C65,'ISO overview'!A:A,'ISO overview'!J:J) -> .kz | K65: Asia | L65: Central Asia | M65: =L65 -> Central Asia
A66: Kirgizië | B66: Kyrgyzstan | C66: KG | D66: KGZ | E66: Som | F66: KGS | G66: KY | H66: EN | I66: +996 | J66: =_xlfn.XLOOKUP(C66,'ISO overview'!A:A,'ISO overview'!J:J) -> .kg | K66: Asia | L66: Central Asia | M66: =L66 -> Central Asia
A67: Tadzjikistan | B67: Tajikistan | C67: TJ | D67: TJK | E67: Tajikistan Ruble | F67: TJS | G67: TG | H67: EN | I67: +992 | J67: =_xlfn.XLOOKUP(C67,'ISO overview'!A:A,'ISO overview'!J:J) -> .tj | K67: Asia | L67: Central Asia | M67: =L67 -> Central Asia
A68: Turkmenistan | B68: Turkmenistan | C68: TM | D68: TKM | E68: Manat | F68: TMT | G68: TK | H68: EN | I68: +993 | J68: =_xlfn.XLOOKUP(C68,'ISO overview'!A:A,'ISO overview'!J:J) -> .tm | K68: Asia | L68: Central Asia | M68: =L68 -> Central Asia
A69: Oezbekistan | B69: Uzbekistan | C69: UZ | D69: UZB | E69: Som | F69: UZS | G69: UZ | H69: EN | I69: +998 | J69: =_xlfn.XLOOKUP(C69,'ISO overview'!A:A,'ISO overview'!J:J) -> .uz | K69: Asia | L69: Central Asia | M69: =L69 -> Central Asia
A70: China | B70: China | C70: CN | D70: CHN | E70: Yuan Renminbi | F70: CNY | G70: ZH | H70: EN | I70: +86 | J70: =_xlfn.XLOOKUP(C70,'ISO overview'!A:A,'ISO overview'!J:J) -> .cn | K70: Asia | L70: Eastern Asia | M70: =L70 -> Eastern Asia
A71: Hongkong | B71: Hong Kong | C71: HK | D71: HKG | E71: HKD | F71: HKD | G71: ZH | H71: EN | I71: +852 | J71: =_xlfn.XLOOKUP(C71,'ISO overview'!A:A,'ISO overview'!J:J) -> .hk | K71: Asia | L71: Eastern Asia | M71: =L71 -> Eastern Asia
A72: Japan | B72: Japan | C72: JP | D72: JPN | E72: Japanese Yen | F72: JPY | G72: JA | H72: EN | I72: +81 | J72: =_xlfn.XLOOKUP(C72,'ISO overview'!A:A,'ISO overview'!J:J) -> .jp | K72: Asia | L72: Eastern Asia | M72: =L72 -> Eastern Asia
A73: Noord-Korea | B73: Korea North | C73: KP | D73: PRK | E73: Won | F73: KPW | G73: KO | H73: EN | I73: +850 | J73: =_xlfn.XLOOKUP(C73,'ISO overview'!A:A,'ISO overview'!J:J) -> .kp | K73: Asia | L73: Eastern Asia | M73: =L73 -> Eastern Asia
A74: Zuid-Korea | B74: Korea South | C74: KR | D74: KOR | E74: Won | F74: KRW | G74: KO | H74: EN | I74: +82 | J74: =_xlfn.XLOOKUP(C74,'ISO overview'!A:A,'ISO overview'!J:J) -> .kr | K74: Asia | L74: Eastern Asia | M74: =L74 -> Eastern Asia
A75: Macau | B75: Macao S.A.R. | C75: MO | D75: MAC | E75: Macanese pataca | F75: MOP | G75: ZH | H75: EN | I75: +853 | J75: =_xlfn.XLOOKUP(C75,'ISO overview'!A:A,'ISO overview'!J:J) -> .mo | K75: Asia | L75: Eastern Asia | M75: =L75 -> Eastern Asia
A76: Macau | B76: Macau | C76: MO | D76: MAC | E76: Pataca | F76: MOP | G76: ZH | H76: EN | I76: +853 | J76: =_xlfn.XLOOKUP(C76,'ISO overview'!A:A,'ISO overview'!J:J) -> .mo | K76: Asia | L76: Eastern Asia | M76: =L76 -> Eastern Asia
... A110: Qatar | B110: Qatar | C110: QA | D110: QAT | E110: Rial | F110: QAR | G110: AR | H110: EN | I110: +974 | J110: =_xlfn.XLOOKUP(C110,'ISO overview'!A:A,'ISO overview'!J:J) -> .qa | K110: Asia | L110: Western Asia | M110: =L110 -> Western Asia
B111: Saudi Arabia | C111: SA | D111: SAU | E111: Riyal | F111: SAR | G111: AR | H111: EN | I111: +966 | J111: =_xlfn.XLOOKUP(C111,'ISO overview'!A:A,'ISO overview'!J:J) -> .sa | K111: Asia | L111: Western Asia | M111: =L111 -> Western Asia
A112: Syrië | B112: Syrian Arab Republic | C112: SY | D112: SYR | E112: Syrian Pound | F112: SYP | G112: AR | H112: EN | I112: +963 | J112: =_xlfn.XLOOKUP(C112,'ISO overview'!A:A,'ISO overview'!J:J) -> .sy | K112: Asia | L112: Western Asia | M112: =L112 -> Western Asia
A113: Turkije | B113: Turkey | C113: TR | D113: TUR | E113: Lira | F113: TRY | G113: TR | H113: EN | I113: +90 | J113: =_xlfn.XLOOKUP(C113,'ISO overview'!A:A,'ISO overview'!J:J) -> .tr | K113: Asia | L113: Western Asia | M113: =L113 -> Western Asia
A114: de Verenigde Arabische Emirate | B114: United Arab Emirates | C114: AE | D114: ARE | E114: Dirham | F114: AED | G114: AR | H114: EN | I114: +971 | J114: =_xlfn.XLOOKUP(C114,'ISO overview'!A:A,'ISO overview'!J:J) -> .ae | K114: Asia | L114: Western Asia | M114: =L114 -> Western Asia
A115: Jemen | B115: Yemen | C115: YE | D115: YEM | E115: Rial | F115: YER | G115: AR | H115: EN | I115: +967 | J115: =_xlfn.XLOOKUP(C115,'ISO overview'!A:A,'ISO overview'!J:J) -> .ye | K115: Asia | L115: Western Asia | M115: =L115 -> Western Asia
A116: Wit-Rusland | B116: Belarus | C116: BY | D116: BLR | E116: Belarus Ruble | F116: BYR | G116: BE | H116: EN | I116: +375 | J116: =_xlfn.XLOOKUP(C116,'ISO overview'!A:A,'ISO overview'!J:J) -> .by | K116: Europe | L116: Eastern Europe | M116: =L116 -> Eastern Europe
A117: Bulgarije | B117: Bulgaria | C117: BG | D117: BGR | E117: Lev | F117: BGN | G117: BG | H117: EN | I117: +359 | J117: =_xlfn.XLOOKUP(C117,'ISO overview'!A:A,'ISO overview'!J:J) -> .bg | K117: Europe | L117: Eastern Europe | M117: =L117 -> Eastern Europe
A118: Tsjechië | B118: Czech Republic | C118: CZ | D118: CZE | E118: Koruna | F118: CZK | G118: CS | H118: EN | I118: +420 | J118: =_xlfn.XLOOKUP(C118,'ISO overview'!A:A,'ISO overview'!J:J) -> .cz | K118: Europe | L118: Eastern Europe | M118: =L118 -> Eastern Europe
A119: Hongarije | B119: Hungary | C119: HU | D119: HUN | E119: Forint | F119: HUF | G119: HU | H119: EN | I119: +36 | J119: =_xlfn.XLOOKUP(C119,'ISO overview'!A:A,'ISO overview'!J:J) -> .hu | K119: Europe | L119: Eastern Europe | M119: =L119 -> Eastern Europe
A120: Moldavië | B120: Moldova Republic of | C120: MD | D120: MDA | E120: Leu | F120: MDL | G120: RO | H120: EN | I120: +373 | J120: =_xlfn.XLOOKUP(C120,'ISO overview'!A:A,'ISO overview'!J:J) -> .md | K120: Europe | L120: Eastern Europe | M120: =L120 -> Eastern Europe
A121: Polen | B121: Poland | C121: PL | D121: POL | E121: Zloty | F121: PLN | G121: PL | H121: EN | I121: +48 | J121: =_xlfn.XLOOKUP(C121,'ISO overview'!A:A,'ISO overview'!J:J) -> .pl | K121: Europe | L121: Eastern Europe | M121: =L121 -> Eastern Europe
A122: Roemenië | B122: Romania | C122: RO | D122: ROU | E122: Leu | F122: RON | G122: RO | H122: EN | I122: +40 | J122: =_xlfn.XLOOKUP(C122,'ISO overview'!A:A,'ISO overview'!J:J) -> .ro | K122: Europe | L122: Eastern Europe | M122: =L122 -> Eastern Europe
A123: Rusland | B123: Russian Federation | C123: RU | D123: RUS | E123: Ruble | F123: RUB | G123: RU | H123: EN | I123: +7 | J123: =_xlfn.XLOOKUP(C123,'ISO overview'!A:A,'ISO overview'!J:J) -> .ru | K123: Europe | L123: Eastern Europe | M123: =L123 -> Eastern Europe
... A125: Oekraïne | B125: Ukraine | C125: UA | D125: UKR | E125: Hryvnia | F125: UAH | G125: UK | H125: EN | I125: +380 | J125: =_xlfn.XLOOKUP(C125,'ISO overview'!A:A,'ISO overview'!J:J) -> .ua | K125: Europe | L125: Eastern Europe | M125: =L125 -> Eastern Europe
A126: Guernsey | B126: Guernsey | C126: GG | D126: GGY | E126: Guernsey pound | F126: GGP | G126: EN | H126: EN | I126: +44-1481 | J126: =_xlfn.XLOOKUP(C126,'ISO overview'!A:A,'ISO overview'!J:J) -> .gg | K126: Europe | L126: Northern Europe | M126: Channel Islands
A127: Jersey | B127: Jersey | C127: JE | D127: JEY | E127: Sterling | F127: GBP | G127: EN | H127: EN | I127: +44-1534 | J127: =_xlfn.XLOOKUP(C127,'ISO overview'!A:A,'ISO overview'!J:J) -> .je | K127: Europe | L127: Northern Europe | M127: Channel Islands
A128: Åland | B128: Aland Islands | C128: AX | D128: ALA | E128: Euro | F128: EUR | G128: SV | H128: EN | I128: +358-18 | J128: =_xlfn.XLOOKUP(C128,'ISO overview'!A:A,'ISO overview'!J:J) -> .ax | K128: Europe | L128: Northern Europe | M128: =L128 -> Northern Europe
A129: Denemarken | B129: Denmark | C129: DK | D129: DNK | E129: Danish Krone | F129: DKK | G129: DA | H129: EN | I129: +45 | J129: =_xlfn.XLOOKUP(C129,'ISO overview'!A:A,'ISO overview'!J:J) -> .dk | K129: Europe | L129: Northern Europe | M129: =L129 -> Northern Europe
A130: Estland | B130: Estonia | C130: EE | D130: EST | E130: Estonian Kroon | F130: EEK | G130: ET | H130: EN | I130: +372 | J130: =_xlfn.XLOOKUP(C130,'ISO overview'!A:A,'ISO overview'!J:J) -> .ee | K130: Europe | L130: Northern Europe | M130: =L130 -> Northern Europe
A131: Faeröer | B131: Faroe Islands | C131: FO | D131: FRO | E131: Danish Krone | F131: DKK | G131: FO | H131: EN | I131: +298 | J131: =_xlfn.XLOOKUP(C131,'ISO overview'!A:A,'ISO overview'!J:J) -> .fo | K131: Europe | L131: Northern Europe | M131: =L131 -> Northern Europe
A132: Finland | B132: Finland | C132: FI | D132: FIN | E132: Euros | F132: EUR | G132: FI | H132: EN | I132: +358 | J132: =_xlfn.XLOOKUP(C132,'ISO overview'!A:A,'ISO overview'!J:J) -> .fi | K132: Europe | L132: Northern Europe | M132: =L132 -> Northern Europe
A133: IJsland | B133: Iceland | C133: IS | D133: ISL | E133: Icelandic Krona | F133: ISK | G133: IS | H133: EN | I133: +354 | J133: =_xlfn.XLOOKUP(C133,'ISO overview'!A:A,'ISO overview'!J:J) -> .is | K133: Europe | L133: Northern Europe | M133: =L133 -> Northern Europe
A134: Ierland | B134: Ireland | C134: IE | D134: IRL | E134: Euros | F134: EUR | G134: EN | H134: EN | I134: +353 | J134: =_xlfn.XLOOKUP(C134,'ISO overview'!A:A,'ISO overview'!J:J) -> .ie | K134: Europe | L134: Northern Europe | M134: =L134 -> Northern Europe
A135: Man | B135: Isle of Man | C135: IM | D135: IMN | E135: Manx pound | F135: GBP | G135: EN | H135: EN | I135: +44-1624 | J135: =_xlfn.XLOOKUP(C135,'ISO overview'!A:A,'ISO overview'!J:J) -> .im | K135: Europe | L135: Northern Europe | M135: =L135 -> Northern Europe
A136: Letland | B136: Latvia | C136: LV | D136: LVA | E136: Lat | F136: LVL | G136: LV | H136: EN | I136: +371 | J136: =_xlfn.XLOOKUP(C136,'ISO overview'!A:A,'ISO overview'!J:J) -> .lv | K136: Europe | L136: Northern Europe | M136: =L136 -> Northern Europe
A137: Litouwen | B137: Lithuania | C137: LT | D137: LTU | E137: Lita | F137: LTL | G137: LT | H137: EN | I137: +370 | J137: =_xlfn.XLOOKUP(C137,'ISO overview'!A:A,'ISO overview'!J:J) -> .lt | K137: Europe | L137: Northern Europe | M137: =L137 -> Northern Europe
A138: Noorwegen | B138: Norway | C138: NO | D138: NOR | E138: Norwegian Krone | F138: NOK | G138: NO | H138: EN | I138: +47 | J138: =_xlfn.XLOOKUP(C138,'ISO overview'!A:A,'ISO overview'!J:J) -> .no | K138: Europe | L138: Northern Europe | M138: =L138 -> Northern Europe
B139: Svalbard and Jan Mayen Islands | C139: SJ | D139: SJM | E139: Norwegian Krone | F139: NOK | G139: NO | H139: EN | I139: +47 | J139: =_xlfn.XLOOKUP(C139,'ISO overview'!A:A,'ISO overview'!J:J) -> .sj | K139: Europe | L139: Northern Europe | M139: =L139 -> Northern Europe
A140: Zweden | B140: Sweden | C140: SE | D140: SWE | E140: Krona | F140: SEK | G140: SV | H140: EN | I140: +46 | J140: =_xlfn.XLOOKUP(C140,'ISO overview'!A:A,'ISO overview'!J:J) -> .se | K140: Europe | L140: Northern Europe | M140: =L140 -> Northern Europe
A141: het Verenigd Koninkri | B141: United Kingdom | C141: GB | D141: GBR | E141: Sterling | F141: GBP | G141: EN | H141: EN | I141: +44 | J141: =_xlfn.XLOOKUP(C141,'ISO overview'!A:A,'ISO overview'!J:J) -> .uk | K141: Europe | L141: Northern Europe | M141: =L141 -> Northern Europe
A142: Albanië | B142: Albania | C142: AL | D142: ALB | E142: Lek | F142: ALL | G142: SQ | H142: EN | I142: +355 | J142: =_xlfn.XLOOKUP(C142,'ISO overview'!A:A,'ISO overview'!J:J) -> .al | K142: Europe | L142: Southern Europe | M142: =L142 -> Southern Europe
A143: Andorra | B143: Andorra | C143: AD | D143: AND | E143: Euros | F143: EUR | G143: CA | H143: EN | I143: +376 | J143: =_xlfn.XLOOKUP(C143,'ISO overview'!A:A,'ISO overview'!J:J) -> .ad | K143: Europe | L143: Southern Europe | M143: =L143 -> Southern Europe
A144: Bosnië en Herzegovina | B144: Bosnia and Herzegovina | C144: BA | D144: BIH | E144: Bosnia and Herzegovina convertible mark | F144: BAM | G144: BS | H144: EN | I144: +387 | J144: =_xlfn.XLOOKUP(C144,'ISO overview'!A:A,'ISO overview'!J:J) -> .ba | K144: Europe | L144: Southern Europe | M144: =L144 -> Southern Europe
A145: Kroatië | B145: Croatia (Hrvatska) | C145: HR | D145: HRV | E145: Croatian Dinar | F145: HRK | G145: HR | H145: EN | I145: +385 | J145: =_xlfn.XLOOKUP(C145,'ISO overview'!A:A,'ISO overview'!J:J) -> .hr | K145: Europe | L145: Southern Europe | M145: =L145 -> Southern Europe
A146: Gibraltar | B146: Gibraltar | C146: GI | D146: GIB | E146: Gibraltar Pound | F146: GIP | G146: EN | H146: EN | I146: +350 | J146: =_xlfn.XLOOKUP(C146,'ISO overview'!A:A,'ISO overview'!J:J) -> .gi | K146: Europe | L146: Southern Europe | M146: =L146 -> Southern Europe
A147: Griekenland | B147: Greece | C147: GR | D147: GRC | E147: Euros | F147: EUR | G147: EL | H147: EN | I147: +30 | J147: =_xlfn.XLOOKUP(C147,'ISO overview'!A:A,'ISO overview'!J:J) -> .gr | K147: Europe | L147: Southern Europe | M147: =L147 -> Southern Europe
A148: Italië | B148: Italy | C148: IT | D148: ITA | E148: Euros | F148: EUR | G148: IT | H148: IT | I148: +39 | J148: =_xlfn.XLOOKUP(C148,'ISO overview'!A:A,'ISO overview'!J:J) -> .it | K148: Europe | L148: Southern Europe | M148: =L148 -> Southern Europe
A149: Noord-Macedonië | B149: Macedonia | C149: MK | D149: MKD | E149: Denar | F149: MKD | G149: MK | H149: EN | I149: +389 | J149: =_xlfn.XLOOKUP(C149,'ISO overview'!A:A,'ISO overview'!J:J) -> .mk | K149: Europe | L149: Southern Europe | M149: =L149 -> Southern Europe
A150: Malta | B150: Malta | C150: MT | D150: MLT | E150: Maltese Lira | F150: MTL | G150: MT | H150: EN | I150: +356 | J150: =_xlfn.XLOOKUP(C150,'ISO overview'!A:A,'ISO overview'!J:J) -> .mt | K150: Europe | L150: Southern Europe | M150: =L150 -> Southern Europe
A151: Montenegro | B151: Montenegro | C151: ME | D151: MNE | E151: Euro | F151: EUR | G151: SR | H151: EN | I151: +382 | J151: =_xlfn.XLOOKUP(C151,'ISO overview'!A:A,'ISO overview'!J:J) -> .me | K151: Europe | L151: Southern Europe | M151: =L151 -> Southern Europe
... A166: Zwitserland | B166: Switzerland | C166: CH | D166: CHE | E166: Swiss Franc | F166: CHF | G166: DE | H166: DE | I166: +41 | J166: =_xlfn.XLOOKUP(C166,'ISO overview'!A:A,'ISO overview'!J:J) -> .ch | K166: Europe | L166: Western Europe | M166: =L166 -> Western Europe
A167: Nederlandse Antillen | B167: Netherlands Antilles | C167: AN | D167: #N/A | E167: Netherlands Antilles Guilder | F167: ANG | G167: HY | H167: EN | I167: +374 | J167: =_xlfn.XLOOKUP(C167,'ISO overview'!A:A,'ISO overview'!J:J) -> .an | K167: North America | L167: Latin America and the Caribbean | M167: Caribbean
A168: Anguilla | B168: Anguilla | C168: AI | D168: AIA | E168: East Caribbean Dollar | F168: XCD | G168: EN | H168: EN | I168: +1-264 | J168: =_xlfn.XLOOKUP(C168,'ISO overview'!A:A,'ISO overview'!J:J) -> .ai | K168: North America | L168: Latin America and the Caribbean | M168: Caribbean
A169: Antigua en Barbuda | B169: Antigua and Barbuda | C169: AG | D169: ATG | E169: East Caribbean Dollar | F169: XCD | G169: EN | H169: EN | I169: +1-268 | J169: =_xlfn.XLOOKUP(C169,'ISO overview'!A:A,'ISO overview'!J:J) -> .ag | K169: North America | L169: Latin America and the Caribbean | M169: Caribbean
A170: Aruba | B170: Aruba | C170: AW | D170: ABW | E170: Netherlands Antilles Guilder | F170: ANG | G170: NL | H170: NL | I170: +297 | J170: =_xlfn.XLOOKUP(C170,'ISO overview'!A:A,'ISO overview'!J:J) -> .aw | K170: North America | L170: Latin America and the Caribbean | M170: Caribbean
...

Sheet Countrycode
A1: Country | B1: Alpha-2 code | C1: Alpha-3 code | D1: Numeric
A2: Afghanistan | B2: AF | C2: AFG | D2: 4
A3: Åland Islands | B3: AX | C3: ALA | D3: 248
A4: Albania | B4: AL | C4: ALB | D4: 8
A5: Algeria | B5: DZ | C5: DZA | D5: 12
A6: American Samoa | B6: AS | C6: ASM | D6: 16
A7: Andorra | B7: AD | C7: AND | D7: 20
A8: Angola | B8: AO | C8: AGO | D8: 24
A9: Anguilla | B9: AI | C9: AIA | D9: 660
A10: Antarctica | B10: AQ | C10: ATA | D10: 10
A11: Antigua and Barbuda | B11: AG | C11: ATG | D11: 28
A12: Argentina | B12: AR | C12: ARG | D12: 32
A13: Armenia | B13: AM | C13: ARM | D13: 51
... A250: Zimbabwe | B250: ZW | C250: ZWE | D250: 716

Sheet Continent
A1: World | B1: Continent | C1: Subregrion | D1: Subsub region | E1: Code | F1: Count | H1: No | I1: Country or Area | J1: ISO-alpha3 Code | K1: M49 Code | L1: Continent | M1: Region 1 | N1: Region 2
B2: Africa | E2: 2 | F2: 60 | H2: 13 | I2: Aruba | J2: ABW | K2: 533 | L2: North America | M2: Caribbean | N2: Latin America and the Caribbean
C3: Northern Africa | E3: 15 | F3: 7 | H3: 1 | I3: Afghanistan | J3: AFG | K3: 4 | L3: Asia | M3: Southern Asia
C4: Sub-Saharan Africa | E4: 202 | F4: 53 | H4: 7 | I4: Angola | J4: AGO | K4: 24 | L4: Africa | M4: Middle Africa | N4: Sub-Saharan Africa
D5: Eastern Africa | E5: 14 | F5: 22 | H5: 8 | I5: Anguilla | J5: AIA | K5: 660 | L5: North America | M5: Caribbean | N5: Latin America and the Caribbean
D6: Middle Africa | E6: 17 | F6: 9 | H6: 2 | I6: Åland Islands | J6: ALA | K6: 248 | L6: Europe | M6: Northern Europe
D7: Southern Africa | E7: 18 | F7: 5 | H7: 3 | I7: Albania | J7: ALB | K7: 8 | L7: Europe | M7: Southern Europe
D8: Western Africa | E8: 11 | F8: 17 | H8: 6 | I8: Andorra | J8: AND | K8: 20 | L8: Europe | M8: Southern Europe
B9: Americas | E9: 19 | F9: 57 | H9: 234 | I9: United Arab Emirates | J9: ARE | K9: 784 | L9: Asia | M9: Western Asia
C10: Latin America and the Caribbean | E10: 419 | F10: 52 | H10: 11 | I10: Argentina | J10: ARG | K10: 32 | L10: South America | M10: South America | N10: Latin America and the Caribbean
D11: Caribbean | E11: 29 | F11: 28 | H11: 12 | I11: Armenia | J11: ARM | K11: 51 | L11: Asia | M11: Western Asia
D12: Central America | E12: 13 | F12: 8 | H12: 5 | I12: American Samoa | J12: ASM | K12: 16 | L12: Oceania | M12: Polynesia
D13: South America | E13: 5 | F13: 16 | H13: 9 | I13: Antarctica | J13: ATA | K13: 10 | L13: Antarctica | M13: Antarctica
C14: Northern America | E14: 21 | F14: 5 | H14: 84 | I14: French Southern Territories | J14: ATF | K14: 260 | L14: Africa | M14: Eastern Africa | N14: Sub-Saharan Africa
B15: Antarctica | E15: 10 | F15: 1 | H15: 10 | I15: Antigua and Barbuda | J15: ATG | K15: 28 | L15: North America | M15: Caribbean | N15: Latin America and the Caribbean
B16: Asia | E16: 142 | F16: 50 | H16: 14 | I16: Australia | J16: AUS | K16: 36 | L16: Oceania | M16: Australia and New Zealand
C17: Central Asia | E17: 143 | F17: 5 | H17: 15 | I17: Austria | J17: AUT | K17: 40 | L17: Europe | M17: Western Europe
C18: Eastern Asia | E18: 30 | F18: 7 | H18: 16 | I18: Azerbaijan | J18: AZE | K18: 31 | L18: Asia | M18: Western Asia
C19: South-eastern Asia | E19: 35 | F19: 11 | H19: 38 | I19: Burundi | J19: BDI | K19: 108 | L19: Africa | M19: Eastern Africa | N19: Sub-Saharan Africa
C20: Southern Asia | E20: 34 | F20: 9 | H20: 22 | I20: Belgium | J20: BEL | K20: 56 | L20: Europe | M20: Western Europe
C21: Western Asia | E21: 145 | F21: 18 | H21: 24 | I21: Benin | J21: BEN | K21: 204 | L21: Africa | M21: Western Africa | N21: Sub-Saharan Africa
B22: Europe | E22: 150 | F22: 52 | H22: 28 | I22: Bonaire, Sint Eustatius and Saba | J22: BES | K22: 535 | L22: North America | M22: Caribbean | N22: Latin America and the Caribbean
C23: Eastern Europe | E23: 151 | F23: 10 | H23: 37 | I23: Burkina Faso | J23: BFA | K23: 854 | L23: Africa | M23: Western Africa | N23: Sub-Saharan Africa
C24: Northern Europe | E24: 154 | F24: 17 | H24: 19 | I24: Bangladesh | J24: BGD | K24: 50 | L24: Asia | M24: Southern Asia
D25: Channel Islands | E25: 830 | F25: 3 | H25: 36 | I25: Bulgaria | J25: BGR | K25: 100 | L25: Europe | M25: Eastern Europe
C26: Southern Europe | E26: 39 | F26: 16 | H26: 18 | I26: Bahrain | J26: BHR | K26: 48 | L26: Asia | M26: Western Asia
C27: Western Europe | E27: 155 | F27: 9 | H27: 17 | I27: Bahamas | J27: BHS | K27: 44 | L27: North America | M27: Caribbean | N27: Latin America and the Caribbean
B28: Oceania | E28: 9 | F28: 29 | H28: 29 | I28: Bosnia and Herzegovina | J28: BIH | K28: 70 | L28: Europe | M28: Southern Europe
C29: Australia and New Zealand | E29: 53 | F29: 6 | H29: 186 | I29: Saint Barthélemy | J29: BLM | K29: 652 | L29: North America | M29: Caribbean | N29: Latin America and the Caribbean
C30: Melanesia | E30: 54 | F30: 5 | H30: 21 | I30: Belarus | J30: BLR | K30: 112 | L30: Europe | M30: Eastern Europe
C31: Micronesia | E31: 57 | F31: 8 | H31: 23 | I31: Belize | J31: BLZ | K31: 84 | L31: North America | M31: Central America | N31: Latin America and the Caribbean
C32: Polynesia | E32: 61 | F32: 10 | H32: 25 | I32: Bermuda | J32: BMU | K32: 60 | L32: North America | M32: Northern America
H33: 27 | I33: Bolivia (Plurinational State of) | J33: BOL | K33: 68 | L33: South America | M33: South America | N33: Latin America and the Caribbean
H34: 32 | I34: Brazil | J34: BRA | K34: 76 | L34: South America | M34: South America | N34: Latin America and the Caribbean
H35: 20 | I35: Barbados | J35: BRB | K35: 52 | L35: North America | M35: Caribbean | N35: Latin America and the Caribbean
H36: 35 | I36: Brunei Darussalam | J36: BRN | K36: 96 | L36: Asia | M36: South-eastern Asia
H37: 26 | I37: Bhutan | J37: BTN | K37: 64 | L37: Asia | M37: Southern Asia
H38: 31 | I38: Bouvet Island | J38: BVT | K38: 74 | L38: South America | M38: South America | N38: Latin America and the Caribbean
H39: 30 | I39: Botswana | J39: BWA | K39: 72 | L39: Africa | M39: Southern Africa | N39: Sub-Saharan Africa
H40: 44 | I40: Central African Republic | J40: CAF | K40: 140 | L40: Africa | M40: Middle Africa | N40: Sub-Saharan Africa
H41: 42 | I41: Canada | J41: CAN | K41: 124 | L41: North America | M41: Northern America
H42: 51 | I42: Cocos (Keeling) Islands | J42: CCK | K42: 166 | L42: Oceania | M42: Australia and New Zealand
H43: 218 | I43: Switzerland | J43: CHE | K43: 756 | L43: Europe | M43: Western Europe
H44: 46 | I44: Chile | J44: CHL | K44: 152 | L44: South America | M44: South America | N44: Latin America and the Caribbean
H45: 47 | I45: China | J45: CHN | K45: 156 | L45: Asia | M45: Eastern Asia
H46: 57 | I46: Côte d’Ivoire | J46: CIV | K46: 384 | L46: Africa | M46: Western Africa | N46: Sub-Saharan Africa
H47: 41 | I47: Cameroon | J47: CMR | K47: 120 | L47: Africa | M47: Middle Africa | N47: Sub-Saharan Africa
H48: 64 | I48: Democratic Republic of the Congo | J48: COD | K48: 180 | L48: Africa | M48: Middle Africa | N48: Sub-Saharan Africa
H49: 54 | I49: Congo | J49: COG | K49: 178 | L49: Africa | M49: Middle Africa | N49: Sub-Saharan Africa
H50: 55 | I50: Cook Islands | J50: COK | K50: 184 | L50: Oceania | M50: Polynesia
H51: 52 | I51: Colombia | J51: COL | K51: 170 | L51: South America | M51: South America | N51: Latin America and the Caribbean
H52: 53 | I52: Comoros | J52: COM | K52: 174 | L52: Africa | M52: Eastern Africa | N52: Sub-Saharan Africa
H53: 39 | I53: Cabo Verde | J53: CPV | K53: 132 | L53: Africa | M53: Western Africa | N53: Sub-Saharan Africa
H54: 56 | I54: Costa Rica | J54: CRI | K54: 188 | L54: North America | M54: Central America | N54: Latin America and the Caribbean
H55: 59 | I55: Cuba | J55: CUB | K55: 192 | L55: North America | M55: Caribbean | N55: Latin America and the Caribbean
H56: 60 | I56: Curaçao | J56: CUW | K56: 531 | L56: North America | M56: Caribbean | N56: Latin America and the Caribbean
H57: 50 | I57: Christmas Island | J57: CXR | K57: 162 | L57: Oceania | M57: Australia and New Zealand
H58: 43 | I58: Cayman Islands | J58: CYM | K58: 136 | L58: North America | M58: Caribbean | N58: Latin America and the Caribbean
H59: 61 | I59: Cyprus | J59: CYP | K59: 196 | L59: Asia | M59: Western Asia
H60: 62 | I60: Czechia | J60: CZE | K60: 203 | L60: Europe | M60: Eastern Europe
H61: 88 | I61: Germany | J61: DEU | K61: 276 | L61: Europe | M61: Western Europe
H62: 66 | I62: Djibouti | J62: DJI | K62: 262 | L62: Africa | M62: Eastern Africa | N62: Sub-Saharan Africa
H63: 67 | I63: Dominica | J63: DMA | K63: 212 | L63: North America | M63: Caribbean | N63: Latin America and the Caribbean
H64: 65 | I64: Denmark | J64: DNK | K64: 208 | L64: Europe | M64: Northern Europe
H65: 68 | I65: Dominican Republic | J65: DOM | K65: 214 | L65: North America | M65: Caribbean | N65: Latin America and the Caribbean
H66: 4 | I66: Algeria | J66: DZA | K66: 12 | L66: Africa | M66: Northern Africa
H67: 69 | I67: Ecuador | J67: ECU | K67: 218 | L67: South America | M67: South America | N67: Latin America and the Caribbean
H68: 70 | I68: Egypt | J68: EGY | K68: 818 | L68: Africa | M68: Northern Africa
H69: 73 | I69: Eritrea | J69: ERI | K69: 232 | L69: Africa | M69: Eastern Africa | N69: Sub-Saharan Africa
H70: 246 | I70: Western Sahara | J70: ESH | K70: 732 | L70: Africa | M70: Northern Africa
H71: 211 | I71: Spain | J71: ESP | K71: 724 | L71: Europe | M71: Southern Europe
H72: 74 | I72: Estonia | J72: EST | K72: 233 | L72: Europe | M72: Northern Europe
H73: 76 | I73: Ethiopia | J73: ETH | K73: 231 | L73: Africa | M73: Eastern Africa | N73: Sub-Saharan Africa
H74: 80 | I74: Finland | J74: FIN | K74: 246 | L74: Europe | M74: Northern Europe
H75: 79 | I75: Fiji | J75: FJI | K75: 242 | L75: Oceania | M75: Melanesia
H76: 77 | I76: Falkland Islands (Malvinas) | J76: FLK | K76: 238 | L76: South America | M76: South America | N76: Latin America and the Caribbean
H77: 81 | I77: France | J77: FRA | K77: 250 | L77: Europe | M77: Western Europe
H78: 78 | I78: Faroe Islands | J78: FRO | K78: 234 | L78: Europe | M78: Northern Europe
H79: 145 | I79: Micronesia (Federated States of) | J79: FSM | K79: 583 | L79: Oceania | M79: Micronesia
H80: 85 | I80: Gabon | J80: GAB | K80: 266 | L80: Africa | M80: Middle Africa | N80: Sub-Saharan Africa
H81: 235 | I81: United Kingdom of Great Britain and Northern Ireland | J81: GBR | K81: 826 | L81: Europe | M81: Northern Europe
H82: 87 | I82: Georgia | J82: GEO | K82: 268 | L82: Asia | M82: Western Asia
H83: 97 | I83: Guernsey | J83: GGY | K83: 831 | L83: Europe | M83: Northern Europe | N83: Channel Islands
H84: 89 | I84: Ghana | J84: GHA | K84: 288 | L84: Africa | M84: Western Africa | N84: Sub-Saharan Africa
H85: 90 | I85: Gibraltar | J85: GIB | K85: 292 | L85: Europe | M85: Southern Europe
H86: 98 | I86: Guinea | J86: GIN | K86: 324 | L86: Africa | M86: Western Africa | N86: Sub-Saharan Africa
H87: 94 | I87: Guadeloupe | J87: GLP | K87: 312 | L87: North America | M87: Caribbean | N87: Latin America and the Caribbean
H88: 86 | I88: Gambia | J88: GMB | K88: 270 | L88: Africa | M88: Western Africa | N88: Sub-Saharan Africa
H89: 99 | I89: Guinea-Bissau | J89: GNB | K89: 624 | L89: Africa | M89: Western Africa | N89: Sub-Saharan Africa
H90: 72 | I90: Equatorial Guinea | J90: GNQ | K90: 226 | L90: Africa | M90: Middle Africa | N90: Sub-Saharan Africa
H91: 91 | I91: Greece | J91: GRC | K91: 300 | L91: Europe | M91: Southern Europe
H92: 93 | I92: Grenada | J92: GRD | K92: 308 | L92: North America | M92: Caribbean | N92: Latin America and the Caribbean
H93: 92 | I93: Greenland | J93: GRL | K93: 304 | L93: North America | M93: Northern America
H94: 96 | I94: Guatemala | J94: GTM | K94: 320 | L94: North America | M94: Central America | N94: Latin America and the Caribbean
H95: 82 | I95: French Guiana | J95: GUF | K95: 254 | L95: South America | M95: South America | N95: Latin America and the Caribbean
H96: 95 | I96: Guam | J96: GUM | K96: 316 | L96: Oceania | M96: Micronesia
H97: 100 | I97: Guyana | J97: GUY | K97: 328 | L97: South America | M97: South America | N97: Latin America and the Caribbean
H98: 48 | I98: China, Hong Kong Special Administrative Region | J98: HKG | K98: 344 | L98: Asia | M98: Eastern Asia
H99: 102 | I99: Heard Island and McDonald Islands | J99: HMD | K99: 334 | L99: Oceania | M99: Australia and New Zealand
H100: 104 | I100: Honduras | J100: HND | K100: 340 | L100: North America | M100: Central America | N100: Latin America and the Caribbean
...

Sheet Sheet4
A1: Langcode in CM | B1: Currendcy in CM
A2: DE | B2: ANG
A3: EN | B3: AUD
A4: ES | B4: BGN
A5: FR | B5: BRL
A6: IT | B6: CAD
A7: NL | B7: CHF
A8: PT | B8: CNY
B9: CZK
B10: DKK
B11: EUR
B12: GBP
B13: HKD
B14: HRK
B15: HUF
B16: IDR
B17: ILS
B18: INR
B19: JPY
B20: KRW
... B35: ZAR

Sheet ISO overview
A1: #ISO | B1: ISO3 | C1: ISO-Numeric | D1: fips | E1: Country | F1: Capital | G1: Area(in sq km) | H1: Population | I1: Continent | J1: tld | K1: CurrencyCode | L1: CurrencyName | M1: Phone with plus | N1: Postal Code Format | O1: Postal Code Regex | P1: Languages | Q1: Official language | R1: geonameid | S1: neighbours | T1: EquivalentFipsCode
A2: AD | B2: AND | C2: 20 | D2: AN | E2: Andorra | F2: Andorra la Vella | G2: 468 | H2: 77006 | I2: EU | J2: .ad | K2: EUR | L2: Euro | M2: +376 | N2: AD### | O2: ^(?:AD)*(\d{3})$ | P2: ca | Q2: ca | R2: 3041565 | S2: ES,FR
A3: AE | B3: ARE | C3: 784 | D3: AE | E3: United Arab Emirates | F3: Abu Dhabi | G3: 82880 | H3: 9630959 | I3: AS | J3: .ae | K3: AED | L3: Dirham | M3: +971 | P3: ar-AE,fa,en,hi,ur | Q3: ar | R3: 290557 | S3: SA,OM
A4: AF | B4: AFG | C4: 4 | D4: AF | E4: Afghanistan | F4: Kabul | G4: 647500 | H4: 37172386 | I4: AS | J4: .af | K4: AFN | L4: Afghani | M4: +93 | P4: fa-AF,ps,uz-AF,tk | Q4: fa | R4: 1149361 | S4: TM,CN,IR,TJ,PK,UZ
A5: AG | B5: ATG | C5: 28 | D5: AC | E5: Antigua and Barbuda | F5: St. John's | G5: 443 | H5: 96286 | I5: NA | J5: .ag | K5: XCD | L5: Dollar | M5: +1-268 | P5: en-AG | Q5: en | R5: 3576396
A6: AI | B6: AIA | C6: 660 | D6: AV | E6: Anguilla | F6: The Valley | G6: 102 | H6: 13254 | I6: NA | J6: .ai | K6: XCD | L6: Dollar | M6: +1-264 | P6: en-AI | Q6: en | R6: 3573511
A7: AL | B7: ALB | C7: 8 | D7: AL | E7: Albania | F7: Tirana | G7: 28748 | H7: 2866376 | I7: EU | J7: .al | K7: ALL | L7: Lek | M7: +355 | N7: #### | O7: ^(\d{4})$ | P7: sq,el | Q7: sq | R7: 783754 | S7: MK,GR,ME,RS,XK
A8: AM | B8: ARM | C8: 51 | D8: AM | E8: Armenia | F8: Yerevan | G8: 29800 | H8: 2951776 | I8: AS | J8: .am | K8: AMD | L8: Dram | M8: +374 | N8: ###### | O8: ^(\d{6})$ | P8: hy | Q8: hy | R8: 174982 | S8: GE,IR,AZ,TR
A9: AO | B9: AGO | C9: 24 | D9: AO | E9: Angola | F9: Luanda | G9: 1246700 | H9: 30809762 | I9: AF | J9: .ao | K9: AOA | L9: Kwanza | M9: +244 | P9: pt-AO | Q9: pt | R9: 3351879 | S9: CD,NA,ZM,CG
A10: AQ | B10: ATA | C10: 10 | D10: AY | E10: Antarctica | G10: 14000000 | H10: 0 | I10: AN | J10: .aq | M10: + | R10: 6697173
A11: AR | B11: ARG | C11: 32 | D11: AR | E11: Argentina | F11: Buenos Aires | G11: 2766890 | H11: 44494502 | I11: SA | J11: .ar | K11: ARS | L11: Peso | M11: +54 | N11: @####@@@ | O11: ^[A-Z]?\d{4}[A-Z]{0,3}$ | P11: es-AR,en,it,de,fr,gn | Q11: es | R11: 3865483 | S11: CL,BO,UY,PY,BR
A12: AS | B12: ASM | C12: 16 | D12: AQ | E12: American Samoa | F12: Pago Pago | G12: 199 | H12: 55465 | I12: OC | J12: .as | K12: USD | L12: Dollar | M12: +1-684 | N12: #####-#### | O12: 96799 | P12: en-AS,sm,to | Q12: en | R12: 5880801
A13: AT | B13: AUT | C13: 40 | D13: AU | E13: Austria | F13: Vienna | G13: 83858 | H13: 8847037 | I13: EU | J13: .at | K13: EUR | L13: Euro | M13: +43 | N13: #### | O13: ^(\d{4})$ | P13: de-AT,hr,hu,sl | Q13: de | R13: 2782113 | S13: CH,DE,HU,SK,CZ,IT,SI,LI
A14: AU | B14: AUS | C14: 36 | D14: AS | E14: Australia | F14: Canberra | G14: 7686850 | H14: 24992369 | I14: OC | J14: .au | K14: AUD | L14: Dollar | M14: +61 | N14: #### | O14: ^(\d{4})$ | P14: en-AU | Q14: en | R14: 2077456
A15: AW | B15: ABW | C15: 533 | D15: AA | E15: Aruba | F15: Oranjestad | G15: 193 | H15: 105845 | I15: NA | J15: .aw | K15: AWG | L15: Guilder | M15: +297 | P15: nl-AW,pap,es,en | Q15: nl | R15: 3577279
A16: AX | B16: ALA | C16: 248 | E16: Aland Islands | F16: Mariehamn | G16: 1580 | H16: 26711 | I16: EU | J16: .ax | K16: EUR | L16: Euro | M16: +358-18 | N16: ##### | O16: ^(?:FI)*(\d{5})$ | P16: sv-AX | Q16: sv | R16: 661882 | T16: FI
A17: AZ | B17: AZE | C17: 31 | D17: AJ | E17: Azerbaijan | F17: Baku | G17: 86600 | H17: 9942334 | I17: AS | J17: .az | K17: AZN | L17: Manat | M17: +994 | N17: AZ #### | O17: ^(?:AZ)*(\d{4})$ | P17: az,ru,hy | Q17: az | R17: 587116 | S17: GE,IR,AM,TR,RU
A18: BA | B18: BIH | C18: 70 | D18: BK | E18: Bosnia and Herzegovina | F18: Sarajevo | G18: 51129 | H18: 3323929 | I18: EU | J18: .ba | K18: BAM | L18: Marka | M18: +387 | N18: ##### | O18: ^(\d{5})$ | P18: bs,hr-BA,sr-BA | Q18: bs | R18: 3277605 | S18: HR,ME,RS
A19: BB | B19: BRB | C19: 52 | D19: BB | E19: Barbados | F19: Bridgetown | G19: 431 | H19: 286641 | I19: NA | J19: .bb | K19: BBD | L19: Dollar | M19: +1-246 | N19: BB##### | O19: ^(?:BB)*(\d{5})$ | P19: en-BB | Q19: en | R19: 3374084
A20: BD | B20: BGD | C20: 50 | D20: BG | E20: Bangladesh | F20: Dhaka | G20: 144000 | H20: 161356039 | I20: AS | J20: .bd | K20: BDT | L20: Taka | M20: +880 | N20: #### | O20: ^(\d{4})$ | P20: bn-BD,en | Q20: bn | R20: 1210997 | S20: MM,IN
A21: BE | B21: BEL | C21: 56 | D21: BE | E21: Belgium | F21: Brussels | G21: 30510 | H21: 11422068 | I21: EU | J21: .be | K21: EUR | L21: Euro | M21: +32 | N21: #### | O21: ^(\d{4})$ | P21: nl-BE,fr-BE,de-BE | Q21: nl | R21: 2802361 | S21: DE,NL,LU,FR
A22: BF | B22: BFA | C22: 854 | D22: UV | E22: Burkina Faso | F22: Ouagadougou | G22: 274200 | H22: 19751535 | I22: AF | J22: .bf | K22: XOF | L22: Franc | M22: +226 | P22: fr-BF,mos | Q22: fr | R22: 2361809 | S22: NE,BJ,GH,CI,TG,ML
A23: BG | B23: BGR | C23: 100 | D23: BU | E23: Bulgaria | F23: Sofia | G23: 110910 | H23: 7000039 | I23: EU | J23: .bg | K23: BGN | L23: Lev | M23: +359 | N23: #### | O23: ^(\d{4})$ | P23: bg,tr-BG,rom | Q23: bg | R23: 732800 | S23: MK,GR,RO,TR,RS
A24: BH | B24: BHR | C24: 48 | D24: BA | E24: Bahrain | F24: Manama | G24: 665 | H24: 1569439 | I24: AS | J24: .bh | K24: BHD | L24: Dinar | M24: +973 | N24: ####|### | O24: ^(\d{3}\d?)$ | P24: ar-BH,en,fa,ur | Q24: ar | R24: 290291
A25: BI | B25: BDI | C25: 108 | D25: BY | E25: Burundi | F25: Gitega | G25: 27830 | H25: 11175378 | I25: AF | J25: .bi | K25: BIF | L25: Franc | M25: +257 | P25: fr-BI,rn | Q25: fr | R25: 433561 | S25: TZ,CD,RW
A26: BJ | B26: BEN | C26: 204 | D26: BN | E26: Benin | F26: Porto-Novo | G26: 112620 | H26: 11485048 | I26: AF | J26: .bj | K26: XOF | L26: Franc | M26: +229 | P26: fr-BJ | Q26: fr | R26: 2395170 | S26: NE,TG,BF,NG
A27: BL | B27: BLM | C27: 652 | D27: TB | E27: Saint Barthelemy | F27: Gustavia | G27: 21 | H27: 8450 | I27: NA | J27: .gp | K27: EUR | L27: Euro | M27: +590 | N27: ##### | O27: ^(\d{5})$ | P27: fr | Q27: fr | R27: 3578476
A28: BM | B28: BMU | C28: 60 | D28: BD | E28: Bermuda | F28: Hamilton | G28: 53 | H28: 63968 | I28: NA | J28: .bm | K28: BMD | L28: Dollar | M28: +1-441 | N28: @@ ## | O28: ^([A-Z]{2}\d{2})$ | P28: en-BM,pt | Q28: en | R28: 3573345
A29: BN | B29: BRN | C29: 96 | D29: BX | E29: Brunei | F29: Bandar Seri Begawan | G29: 5770 | H29: 428962 | I29: AS | J29: .bn | K29: BND | L29: Dollar | M29: +673 | N29: @@#### | O29: ^([A-Z]{2}\d{4})$ | P29: ms-BN,en-BN | Q29: ms | R29: 1820814 | S29: MY
A30: BO | B30: BOL | C30: 68 | D30: BL | E30: Bolivia | F30: Sucre | G30: 1098580 | H30: 11353142 | I30: SA | J30: .bo | K30: BOB | L30: Boliviano | M30: +591 | P30: es-BO,qu,ay | Q30: es | R30: 3923057 | S30: PE,CL,PY,BR,AR
A31: BQ | B31: BES | C31: 535 | E31: Bonaire, Saint Eustatius and Saba | G31: 328 | H31: 18012 | I31: NA | J31: .bq | K31: USD | L31: Dollar | M31: +599 | P31: nl,pap,en | Q31: nl | R31: 7626844
A32: BR | B32: BRA | C32: 76 | D32: BR | E32: Brazil | F32: Brasilia | G32: 8511965 | H32: 209469333 | I32: SA | J32: .br | K32: BRL | L32: Real | M32: +55 | N32: #####-### | O32: ^\d{5}-\d{3}$ | P32: pt-BR,es,en,fr | Q32: pt | R32: 3469034 | S32: SR,PE,BO,UY,GY,PY,GF,VE,CO,AR
A33: BS | B33: BHS | C33: 44 | D33: BF | E33: Bahamas | F33: Nassau | G33: 13940 | H33: 385640 | I33: NA | J33: .bs | K33: BSD | L33: Dollar | M33: +1-242 | P33: en-BS | Q33: en | R33: 3572887
A34: BT | B34: BTN | C34: 64 | D34: BT | E34: Bhutan | F34: Thimphu | G34: 47000 | H34: 754394 | I34: AS | J34: .bt | K34: BTN | L34: Ngultrum | M34: +975 | P34: dz | Q34: dz | R34: 1252634 | S34: CN,IN
A35: BV | B35: BVT | C35: 74 | D35: BV | E35: Bouvet Island | G35: 49 | H35: 0 | I35: AN | J35: .bv | K35: NOK | L35: Krone | M35: + | R35: 3371123
A36: BW | B36: BWA | C36: 72 | D36: BC | E36: Botswana | F36: Gaborone | G36: 600370 | H36: 2254126 | I36: AF | J36: .bw | K36: BWP | L36: Pula | M36: +267 | P36: en-BW,tn-BW | Q36: en | R36: 933860 | S36: ZW,ZA,NA
A37: BY | B37: BLR | C37: 112 | D37: BO | E37: Belarus | F37: Minsk | G37: 207600 | H37: 9485386 | I37: EU | J37: .by | K37: BYN | L37: Belarusian ruble | M37: +375 | N37: ###### | O37: ^(\d{6})$ | P37: be,ru | Q37: be | R37: 630336 | S37: PL,LT,UA,RU,LV
A38: BZ | B38: BLZ | C38: 84 | D38: BH | E38: Belize | F38: Belmopan | G38: 22966 | H38: 383071 | I38: NA | J38: .bz | K38: BZD | L38: Dollar | M38: +501 | P38: en-BZ,es | Q38: en | R38: 3582678 | S38: GT,MX
A39: CA | B39: CAN | C39: 124 | D39: CA | E39: Canada | F39: Ottawa | G39: 9984670 | H39: 37058856 | I39: NA | J39: .ca | K39: CAD | L39: Dollar | M39: +1 | N39: @#@ #@# | O39: ^([ABCEGHJKLMNPRSTVXY]\d[ABCEGHJKLMNPRSTVWXYZ]) ?(\d[ABCEGHJKLMNPRSTVWXYZ]\d)$ | P39: en-CA,fr-CA,iu | Q39: en | R39: 6251999 | S39: US
A40: CC | B40: CCK | C40: 166 | D40: CK | E40: Cocos Islands | F40: West Island | G40: 14 | H40: 628 | I40: AS | J40: .cc | K40: AUD | L40: Dollar | M40: +61 | P40: ms-CC,en | Q40: ms | R40: 1547376
A41: CD | B41: COD | C41: 180 | D41: CG | E41: Democratic Republic of the Congo | F41: Kinshasa | G41: 2345410 | H41: 84068091 | I41: AF | J41: .cd | K41: CDF | L41: Franc | M41: +243 | P41: fr-CD,ln,ktu,kg,sw,lua | Q41: fr | R41: 203312 | S41: TZ,CF,SS,RW,ZM,BI,UG,CG,AO
A42: CF | B42: CAF | C42: 140 | D42: CT | E42: Central African Republic | F42: Bangui | G42: 622984 | H42: 4666377 | I42: AF | J42: .cf | K42: XAF | L42: Franc | M42: +236 | P42: fr-CF,sg,ln,kg | Q42: fr | R42: 239880 | S42: TD,SD,CD,SS,CM,CG
A43: CG | B43: COG | C43: 178 | D43: CF | E43: Republic of the Congo | F43: Brazzaville | G43: 342000 | H43: 5244363 | I43: AF | J43: .cg | K43: XAF | L43: Franc | M43: +242 | P43: fr-CG,kg,ln-CG | Q43: fr | R43: 2260494 | S43: CF,GA,CD,CM,AO
A44: CH | B44: CHE | C44: 756 | D44: SZ | E44: Switzerland | F44: Bern | G44: 41290 | H44: 8516543 | I44: EU | J44: .ch | K44: CHF | L44: Franc | M44: +41 | N44: #### | O44: ^(\d{4})$ | P44: de-CH,fr-CH,it-CH,rm | Q44: de | R44: 2658434 | S44: DE,IT,LI,FR,AT
A45: CI | B45: CIV | C45: 384 | D45: IV | E45: Ivory Coast | F45: Yamoussoukro | G45: 322460 | H45: 25069229 | I45: AF | J45: .ci | K45: XOF | L45: Franc | M45: +225 | P45: fr-CI | Q45: fr | R45: 2287781 | S45: LR,GH,GN,BF,ML
A46: CK | B46: COK | C46: 184 | D46: CW | E46: Cook Islands | F46: Avarua | G46: 240 | H46: 21388 | I46: OC | J46: .ck | K46: NZD | L46: Dollar | M46: +682 | P46: en-CK,mi | Q46: en | R46: 1899402
A47: CL | B47: CHL | C47: 152 | D47: CI | E47: Chile | F47: Santiago | G47: 756950 | H47: 18729160 | I47: SA | J47: .cl | K47: CLP | L47: Peso | M47: +56 | N47: ####### | O47: ^(\d{7})$ | P47: es-CL | Q47: es | R47: 3895114 | S47: PE,BO,AR
A48: CM | B48: CMR | C48: 120 | D48: CM | E48: Cameroon | F48: Yaounde | G48: 475440 | H48: 25216237 | I48: AF | J48: .cm | K48: XAF | L48: Franc | M48: +237 | P48: en-CM,fr-CM | Q48: en | R48: 2233387 | S48: TD,CF,GA,GQ,CG,NG
A49: CN | B49: CHN | C49: 156 | D49: CH | E49: China | F49: Beijing | G49: 9596960 | H49: 1411778724 | I49: AS | J49: .cn | K49: CNY | L49: Yuan Renminbi | M49: +86 | N49: ###### | O49: ^(\d{6})$ | P49: zh-CN,yue,wuu,dta,ug,za | Q49: zh | R49: 1814991 | S49: LA,BT,TJ,KZ,MN,AF,NP,MM,KG,PK,KP,RU,VN,IN
A50: CO | B50: COL | C50: 170 | D50: CO | E50: Colombia | F50: Bogota | G50: 1138910 | H50: 49648685 | I50: SA | J50: .co | K50: COP | L50: Peso | M50: +57 | N50: ###### | O50: ^(\d{6})$ | P50: es-CO | Q50: es | R50: 3686110 | S50: EC,PE,PA,BR,VE
A51: CR | B51: CRI | C51: 188 | D51: CS | E51: Costa Rica | F51: San Jose | G51: 51100 | H51: 4999441 | I51: NA | J51: .cr | K51: CRC | L51: Colon | M51: +506 | N51: ##### | O51: ^(\d{5})$ | P51: es-CR,en | Q51: es | R51: 3624060 | S51: PA,NI
A52: CU | B52: CUB | C52: 192 | D52: CU | E52: Cuba | F52: Havana | G52: 110860 | H52: 11338138 | I52: NA | J52: .cu | K52: CUP | L52: Peso | M52: +53 | N52: CP ##### | O52: ^(?:CP)*(\d{5})$ | P52: es-CU,pap | Q52: es | R52: 3562981 | S52: US
A53: CV | B53: CPV | C53: 132 | D53: CV | E53: Cabo Verde | F53: Praia | G53: 4033 | H53: 543767 | I53: AF | J53: .cv | K53: CVE | L53: Escudo | M53: +238 | N53: #### | O53: ^(\d{4})$ | P53: pt-CV | Q53: pt | R53: 3374766
A54: CW | B54: CUW | C54: 531 | D54: UC | E54: Curacao | F54: Willemstad | G54: 444 | H54: 159849 | I54: NA | J54: .cw | K54: ANG | L54: Guilder | M54: +599 | P54: nl,pap | Q54: nl | R54: 7626836
A55: CX | B55: CXR | C55: 162 | D55: KT | E55: Christmas Island | F55: Flying Fish Cove | G55: 135 | H55: 1500 | I55: OC | J55: .cx | K55: AUD | L55: Dollar | M55: +61 | N55: #### | O55: ^(\d{4})$ | P55: en,zh,ms-CX | Q55: en | R55: 2078138
A56: CY | B56: CYP | C56: 196 | D56: CY | E56: Cyprus | F56: Nicosia | G56: 9250 | H56: 1189265 | I56: EU | J56: .cy | K56: EUR | L56: Euro | M56: +357 | N56: #### | O56: ^(\d{4})$ | P56: el-CY,tr-CY,en | Q56: el | R56: 146669
A57: CZ | B57: CZE | C57: 203 | D57: EZ | E57: Czechia | F57: Prague | G57: 78866 | H57: 10625695 | I57: EU | J57: .cz | K57: CZK | L57: Koruna | M57: +420 | N57: ### ## | O57: ^\d{3}\s?\d{2}$ | P57: cs,sk | Q57: cs | R57: 3077311 | S57: PL,DE,SK,AT
A58: DE | B58: DEU | C58: 276 | D58: GM | E58: Germany | F58: Berlin | G58: 357021 | H58: 82927922 | I58: EU | J58: .de | K58: EUR | L58: Euro | M58: +49 | N58: ##### | O58: ^(\d{5})$ | P58: de | Q58: de | R58: 2921044 | S58: CH,PL,NL,DK,BE,CZ,LU,FR,AT
A59: DJ | B59: DJI | C59: 262 | D59: DJ | E59: Djibouti | F59: Djibouti | G59: 23000 | H59: 958920 | I59: AF | J59: .dj | K59: DJF | L59: Franc | M59: +253 | P59: fr-DJ,ar,so-DJ,aa | Q59: fr | R59: 223816 | S59: ER,ET,SO
A60: DK | B60: DNK | C60: 208 | D60: DA | E60: Denmark | F60: Copenhagen | G60: 43094 | H60: 5797446 | I60: EU | J60: .dk | K60: DKK | L60: Krone | M60: +45 | N60: #### | O60: ^(\d{4})$ | P60: da-DK,en,fo,de-DK | Q60: da | R60: 2623032 | S60: DE
A61: DM | B61: DMA | C61: 212 | D61: DO | E61: Dominica | F61: Roseau | G61: 754 | H61: 71625 | I61: NA | J61: .dm | K61: XCD | L61: Dollar | M61: +1-767 | P61: en-DM | Q61: en | R61: 3575830
A62: DO | B62: DOM | C62: 214 | D62: DR | E62: Dominican Republic | F62: Santo Domingo | G62: 48730 | H62: 10627165 | I62: NA | J62: .do | K62: DOP | L62: Peso | M62: +1-809 | N62: ##### | O62: ^(\d{5})$ | P62: es-DO | Q62: es | R62: 3508796 | S62: HT
A63: DZ | B63: DZA | C63: 12 | D63: AG | E63: Algeria | F63: Algiers | G63: 2381740 | H63: 42228429 | I63: AF | J63: .dz | K63: DZD | L63: Dinar | M63: +213 | N63: ##### | O63: ^(\d{5})$ | P63: ar-DZ | Q63: ar | R63: 2589581 | S63: NE,EH,LY,MR,TN,MA,ML
A64: EC | B64: ECU | C64: 218 | D64: EC | E64: Ecuador | F64: Quito | G64: 283560 | H64: 17084357 | I64: SA | J64: .ec | K64: USD | L64: Dollar | M64: +593 | N64: @####@ | O64: ^([a-zA-Z]\d{4}[a-zA-Z])$ | P64: es-EC | Q64: es | R64: 3658394 | S64: PE,CO
A65: EE | B65: EST | C65: 233 | D65: EN | E65: Estonia | F65: Tallinn | G65: 45226 | H65: 1320884 | I65: EU | J65: .ee | K65: EUR | L65: Euro | M65: +372 | N65: ##### | O65: ^(\d{5})$ | P65: et,ru | Q65: et | R65: 453733 | S65: RU,LV
A66: EG | B66: EGY | C66: 818 | D66: EG | E66: Egypt | F66: Cairo | G66: 1001450 | H66: 98423595 | I66: AF | J66: .eg | K66: EGP | L66: Pound | M66: +20 | N66: ##### | O66: ^(\d{5})$ | P66: ar-EG,en,fr | Q66: ar | R66: 357994 | S66: LY,SD,IL,PS
A67: EH | B67: ESH | C67: 732 | D67: WI | E67: Western Sahara | F67: El-Aaiun | G67: 266000 | H67: 273008 | I67: AF | J67: .eh | K67: MAD | L67: Dirham | M67: +212 | P67: ar,mey | Q67: ar | R67: 2461445 | S67: DZ,MR,MA
A68: ER | B68: ERI | C68: 232 | D68: ER | E68: Eritrea | F68: Asmara | G68: 121320 | H68: 6209262 | I68: AF | J68: .er | K68: ERN | L68: Nakfa | M68: +291 | P68: aa-ER,ar,tig,kun,ti-ER | Q68: aa | R68: 338010 | S68: ET,SD,DJ
A69: ES | B69: ESP | C69: 724 | D69: SP | E69: Spain | F69: Madrid | G69: 504782 | H69: 46723749 | I69: EU | J69: .es | K69: EUR | L69: Euro | M69: +34 | N69: ##### | O69: ^(\d{5})$ | P69: es-ES,ca,gl,eu,oc | Q69: es | R69: 2510769 | S69: AD,PT,GI,FR,MA
A70: ET | B70: ETH | C70: 231 | D70: ET | E70: Ethiopia | F70: Addis Ababa | G70: 1127127 | H70: 109224559 | I70: AF | J70: .et | K70: ETB | L70: Birr | M70: +251 | N70: #### | O70: ^(\d{4})$ | P70: am,en-ET,om-ET,ti-ET,so-ET,sid | Q70: am | R70: 337996 | S70: ER,KE,SD,SS,SO,DJ
A71: FI | B71: FIN | C71: 246 | D71: FI | E71: Finland | F71: Helsinki | G71: 337030 | H71: 5518050 | I71: EU | J71: .fi | K71: EUR | L71: Euro | M71: +358 | N71: ##### | O71: ^(?:FI)*(\d{5})$ | P71: fi-FI,sv-FI,smn | Q71: fi | R71: 660013 | S71: NO,RU,SE
A72: FJ | B72: FJI | C72: 242 | D72: FJ | E72: Fiji | F72: Suva | G72: 18270 | H72: 883483 | I72: OC | J72: .fj | K72: FJD | L72: Dollar | M72: +679 | P72: en-FJ,fj | Q72: en | R72: 2205218
A73: FK | B73: FLK | C73: 238 | D73: FK | E73: Falkland Islands | F73: Stanley | G73: 12173 | H73: 2638 | I73: SA | J73: .fk | K73: FKP | L73: Pound | M73: +500 | P73: en-FK | Q73: en | R73: 3474414
A74: FM | B74: FSM | C74: 583 | D74: FM | E74: Micronesia | F74: Palikir | G74: 702 | H74: 112640 | I74: OC | J74: .fm | K74: USD | L74: Dollar | M74: +691 | N74: ##### | O74: ^(\d{5})$ | P74: en-FM,chk,pon,yap,kos,uli,woe,nkr,kpg | Q74: en | R74: 2081918
A75: FO | B75: FRO | C75: 234 | D75: FO | E75: Faroe Islands | F75: Torshavn | G75: 1399 | H75: 48497 | I75: EU | J75: .fo | K75: DKK | L75: Krone | M75: +298 | N75: ### | O75: ^(?:FO)*(\d{3})$ | P75: fo,da-FO | Q75: fo | R75: 2622320
A76: FR | B76: FRA | C76: 250 | D76: FR | E76: France | F76: Paris | G76: 547030 | H76: 66987244 | I76: EU | J76: .fr | K76: EUR | L76: Euro | M76: +33 | N76: ##### | O76: ^(\d{5})$ | P76: fr-FR,frp,br,co,ca,eu,oc | Q76: fr | R76: 3017382 | S76: CH,DE,BE,LU,IT,AD,MC,ES
A77: GA | B77: GAB | C77: 266 | D77: GB | E77: Gabon | F77: Libreville | G77: 267667 | H77: 2119275 | I77: AF | J77: .ga | K77: XAF | L77: Franc | M77: +241 | P77: fr-GA | Q77: fr | R77: 2400553 | S77: CM,GQ,CG
A78: GB | B78: GBR | C78: 826 | D78: UK | E78: United Kingdom | F78: London | G78: 244820 | H78: 66488991 | I78: EU | J78: .uk | K78: GBP | L78: Pound | M78: +44 | N78: @# #@@|@## #@@|@@# #@@|@@## #@@|@#@ #@@|@@#@ #@@|GIR0AA | O78: ^([Gg][Ii][Rr]\s?0[Aa]{2})|((([A-Za-z][0-9]{1,2})|(([A-Za-z][A-Ha-hJ-Yj-y][0-9]{1,2})|(([A-Za-z][0-9][A-Za-z])|([A-Za-z][A-Ha-hJ-Yj-y][0-9]?[A-Za-z]))))\s?[0-9][A-Za-z]{2})$ | P78: en-GB,cy-GB,gd | Q78: en | R78: 2635167 | S78: IE
A79: GD | B79: GRD | C79: 308 | D79: GJ | E79: Grenada | F79: St. George's | G79: 344 | H79: 111454 | I79: NA | J79: .gd | K79: XCD | L79: Dollar | M79: +1-473 | P79: en-GD | Q79: en | R79: 3580239
A80: GE | B80: GEO | C80: 268 | D80: GG | E80: Georgia | F80: Tbilisi | G80: 69700 | H80: 3731000 | I80: AS | J80: .ge | K80: GEL | L80: Lari | M80: +995 | N80: #### | O80: ^(\d{4})$ | P80: ka,ru,hy,az | Q80: ka | R80: 614540 | S80: AM,AZ,TR,RU
A81: GF | B81: GUF | C81: 254 | D81: FG | E81: French Guiana | F81: Cayenne | G81: 91000 | H81: 195506 | I81: SA | J81: .gf | K81: EUR | L81: Euro | M81: +594 | N81: ##### | O81: ^((97|98)3\d{2})$ | P81: fr-GF | Q81: fr | R81: 3381670 | S81: SR,BR
A82: GG | B82: GGY | C82: 831 | D82: GK | E82: Guernsey | F82: St Peter Port | G82: 78 | H82: 65228 | I82: EU | J82: .gg | K82: GBP | L82: Pound | M82: +44-1481 | N82: @# #@@|@## #@@|@@# #@@|@@## #@@|@#@ #@@|@@#@ #@@|GIR0AA | O82: ^((?:(?:[A-PR-UWYZ][A-HK-Y]\d[ABEHMNPRV-Y0-9]|[A-PR-UWYZ]\d[A-HJKPS-UW0-9])\s\d[ABD-HJLNP-UW-Z]{2})|GIR\s?0AA)$ | P82: en,nrf | Q82: en | R82: 3042362
A83: GH | B83: GHA | C83: 288 | D83: GH | E83: Ghana | F83: Accra | G83: 239460 | H83: 29767108 | I83: AF | J83: .gh | K83: GHS | L83: Cedi | M83: +233 | P83: en-GH,ak,ee,tw | Q83: en | R83: 2300660 | S83: CI,TG,BF
A84: GI | B84: GIB | C84: 292 | D84: GI | E84: Gibraltar | F84: Gibraltar | G84: 6.5 | H84: 33718 | I84: EU | J84: .gi | K84: GIP | L84: Pound | M84: +350 | P84: en-GI,es,it,pt | Q84: en | R84: 2411586 | S84: ES
A85: GL | B85: GRL | C85: 304 | D85: GL | E85: Greenland | F85: Nuuk | G85: 2166086 | H85: 56025 | I85: NA | J85: .gl | K85: DKK | L85: Krone | M85: +299 | N85: #### | O85: ^(\d{4})$ | P85: kl,da-GL,en | Q85: kl | R85: 3425505
A86: GM | B86: GMB | C86: 270 | D86: GA | E86: Gambia | F86: Banjul | G86: 11300 | H86: 2280102 | I86: AF | J86: .gm | K86: GMD | L86: Dalasi | M86: +220 | P86: en-GM,mnk,wof,wo,ff | Q86: en | R86: 2413451 | S86: SN
A87: GN | B87: GIN | C87: 324 | D87: GV | E87: Guinea | F87: Conakry | G87: 245857 | H87: 12414318 | I87: AF | J87: .gn | K87: GNF | L87: Franc | M87: +224 | P87: fr-GN | Q87: fr | R87: 2420477 | S87: LR,SN,SL,CI,GW,ML
A88: GP | B88: GLP | C88: 312 | D88: GP | E88: Guadeloupe | F88: Basse-Terre | G88: 1780 | H88: 443000 | I88: NA | J88: .gp | K88: EUR | L88: Euro | M88: +590 | N88: ##### | O88: ^((97|98)\d{3})$ | P88: fr-GP | Q88: fr | R88: 3579143
A89: GQ | B89: GNQ | C89: 226 | D89: EK | E89: Equatorial Guinea | F89: Malabo | G89: 28051 | H89: 1308974 | I89: AF | J89: .gq | K89: XAF | L89: Franc | M89: +240 | P89: es-GQ,fr,pt | Q89: es | R89: 2309096 | S89: GA,CM
A90: GR | B90: GRC | C90: 300 | D90: GR | E90: Greece | F90: Athens | G90: 131940 | H90: 10727668 | I90: EU | J90: .gr | K90: EUR | L90: Euro | M90: +30 | N90: ### ## | O90: ^(\d{5})$ | P90: el-GR,en,fr | Q90: el | R90: 390903 | S90: AL,MK,TR,BG
A91: GS | B91: SGS | C91: 239 | D91: SX | E91: South Georgia and the South Sandwich Islands | F91: Grytviken | G91: 3903 | H91: 30 | I91: AN | J91: .gs | K91: GBP | L91: Pound | M91: + | P91: en | Q91: en | R91: 3474415
A92: GT | B92: GTM | C92: 320 | D92: GT | E92: Guatemala | F92: Guatemala City | G92: 108890 | H92: 17247807 | I92: NA | J92: .gt | K92: GTQ | L92: Quetzal | M92: +502 | N92: ##### | O92: ^(\d{5})$ | P92: es-GT | Q92: es | R92: 3595528 | S92: MX,HN,BZ,SV
A93: GU | B93: GUM | C93: 316 | D93: GQ | E93: Guam | F93: Hagatna | G93: 549 | H93: 165768 | I93: OC | J93: .gu | K93: USD | L93: Dollar | M93: +1-671 | N93: 969## | O93: ^(969\d{2})$ | P93: en-GU,ch-GU | Q93: en | R93: 4043988
A94: GW | B94: GNB | C94: 624 | D94: PU | E94: Guinea-Bissau | F94: Bissau | G94: 36120 | H94: 1874309 | I94: AF | J94: .gw | K94: XOF | L94: Franc | M94: +245 | N94: #### | O94: ^(\d{4})$ | P94: pt-GW,pov | Q94: pt | R94: 2372248 | S94: SN,GN
A95: GY | B95: GUY | C95: 328 | D95: GY | E95: Guyana | F95: Georgetown | G95: 214970 | H95: 779004 | I95: SA | J95: .gy | K95: GYD | L95: Dollar | M95: +592 | P95: en-GY | Q95: en | R95: 3378535 | S95: SR,BR,VE
A96: HK | B96: HKG | C96: 344 | D96: HK | E96: Hong Kong | F96: Hong Kong | G96: 1092 | H96: 7451000 | I96: AS | J96: .hk | K96: HKD | L96: Dollar | M96: +852 | P96: zh-HK,yue,zh,en | Q96: zh | R96: 1819730
A97: HM | B97: HMD | C97: 334 | D97: HM | E97: Heard Island and McDonald Islands | G97: 412 | H97: 0 | I97: AN | J97: .hm | K97: AUD | L97: Dollar | M97: + | R97: 1547314
A98: HN | B98: HND | C98: 340 | D98: HO | E98: Honduras | F98: Tegucigalpa | G98: 112090 | H98: 9587522 | I98: NA | J98: .hn | K98: HNL | L98: Lempira | M98: +504 | N98: @@#### | O98: ^([A-Z]{2}\d{4})$ | P98: es-HN,cab,miq | Q98: es | R98: 3608932 | S98: GT,NI,SV
A99: HR | B99: HRV | C99: 191 | D99: HR | E99: Croatia | F99: Zagreb | G99: 56542 | H99: 4089400 | I99: EU | J99: .hr | K99: EUR | L99: Euro | M99: +385 | N99: ##### | O99: ^(?:HR)*(\d{5})$ | P99: hr-HR,sr | Q99: hr | R99: 3202326 | S99: HU,SI,BA,ME,RS
A100: HT | B100: HTI | C100: 332 | D100: HA | E100: Haiti | F100: Port-au-Prince | G100: 27750 | H100: 11123176 | I100: NA | J100: .ht | K100: HTG | L100: Gourde | M100: +509 | N100: HT#### | O100: ^(?:HT)*(\d{4})$ | P100: ht,fr-HT | Q100: ht | R100: 3723988 | S100: DO
...
